PyJSH/__init__.py
PyJSH/console/__init__.py
PyJSH/console/exc.py
PyJSH/console/input.py
PyJSH/console/log.py
PyJSH/console/massiv.py
PyJSH/console/num.py
PyJSH/window/__init__.py
PyJSH/window/color.py
PyJSH/window/figure.py
PyJSH/window/open.py
pyjsh-0.2.3.dist-info/WHEEL
pyjsh-0.2.3.dist-info/METADATA
pyjsh-0.2.3.dist-info/RECORD
