Metadata-Version: 2.4
Name: PyJSH
Version: 0.2.3
Summary: Educational graphics and console toolkit built on pygame.
Author-email: Шыңғысхан <your_email@example.com>
Requires-Python: >=3.8
Requires-Dist: pygame>=2.0.0
